abuseipdb2iptables/__init__.py
abuseipdb2iptables/__main__.py
abuseipdb2iptables/cli.py
abuseipdb2iptables-0.2.1.dist-info/LICENSE
abuseipdb2iptables-0.2.1.dist-info/METADATA
abuseipdb2iptables-0.2.1.dist-info/WHEEL
abuseipdb2iptables-0.2.1.dist-info/entry_points.txt
abuseipdb2iptables-0.2.1.dist-info/RECORD
