Metadata-Version: 2.1
Name: abuseipdb2iptables
Version: 0.2.1
Summary: 
Author: Bruno Thomas
Author-email: bruno@barreverte.fr
Requires-Python: >=3.8,<4.0
Classifier: Programming Language :: Python :: 3
Classifier: Programming Language :: Python :: 3.8
Classifier: Programming Language :: Python :: 3.9
Classifier: Programming Language :: Python :: 3.10
Classifier: Programming Language :: Python :: 3.11
Classifier: Programming Language :: Python :: 3.12
